LICENSE
MANIFEST.in
README.md
setup.cfg
setup.py
graphstack/__init__.py
graphstack/base.py
graphstack.egg-info/PKG-INFO
graphstack.egg-info/SOURCES.txt
graphstack.egg-info/dependency_links.txt
graphstack.egg-info/pbr.json
graphstack.egg-info/requires.txt
graphstack.egg-info/top_level.txt