Metadata-Version: 1.1
Name: graphstack
Version: 0.1.0
Summary: graphstack
Home-page: https://github.com/3ptscience/graphstack
Author: Brendan Smithyman
Author-email: brendan@3ptscience.com
License: MIT
Download-URL: https://github.com/3ptscience/graphstack
Keywords: dictionary class attribute
Platform: Windows
Platform: Linux
Platform: Solaris
Platform: Mac OS-X
Platform: Unix
Classifier: Development Status :: 3 - Alpha
Classifier: Intended Audience :: Developers
Classifier: License :: OSI Approved :: MIT License
Classifier: Programming Language :: Python
Classifier: Programming Language :: Python :: 2.7
Classifier: Programming Language :: Python :: 3.3
Classifier: Programming Language :: Python :: 3.4
Classifier: Programming Language :: Python :: 3.5
Classifier: Operating System :: Microsoft :: Windows
Classifier: Operating System :: POSIX
Classifier: Operating System :: Unix
Classifier: Operating System :: MacOS
Classifier: Natural Language :: English
